bluetooth_mesh/network/crypto.py
bluetooth_mesh/network/mesh.py
bluetooth_mesh/network/provisioning.py
bluetooth_mesh_network-0.9.4.dist-info/licenses/LICENSE
bluetooth_mesh_network-0.9.4.dist-info/METADATA
bluetooth_mesh_network-0.9.4.dist-info/WHEEL
bluetooth_mesh_network-0.9.4.dist-info/top_level.txt
bluetooth_mesh_network-0.9.4.dist-info/RECORD
