Metadata-Version: 2.4
Name: bluetooth-mesh-network
Version: 0.9.4
Author-email: Michał Lowas-Rzechonek <michal.lowas-rzechonek@silvair.com>, Amadeusz Herzog <amadeusz.hercog@silvair.com>, Jakub Witowski <jakub.witowski@silvair.com>, Kamil Janowski <kamil.janowski@silvair.com>, Przemysław Fierek <przemyslaw.fierek@silvair.com>, Rafał Gajda <rafal.gajda@silvair.com>
Classifier: Development Status :: 4 - Beta
Classifier: Intended Audience :: Developers
Classifier: License :: OSI Approved :: GNU General Public License v2 (GPLv2)
Classifier: Operating System :: POSIX :: Linux
Classifier: Programming Language :: Python :: 3 :: Only
Classifier: Programming Language :: Python :: Implementation :: CPython
Classifier: Topic :: System :: Networking
License-File: LICENSE
Requires-Dist: bitstring<4.0.0,>=3.1.5
Requires-Dist: bluetooth-mesh-messages>=0.9
Requires-Dist: construct<2.9.46,>=2.9.45
Requires-Dist: crc==0.3.0
Requires-Dist: cryptography>=2.3.1
Requires-Dist: ecdsa==0.19.1
Provides-Extra: test
Requires-Dist: black; extra == "test"
Requires-Dist: isort; extra == "test"
Requires-Dist: pytest; extra == "test"
Requires-Dist: ruff; extra == "test"
Dynamic: license-file
